[{"timestamp":1654599137126,"files":[{"filename":"bundle.*****.js","previous":18732,"size":25278,"diff":6546},{"filename":"polyfills.*****.js","previous":2136,"size":2136,"diff":0},{"filename":"assets/css/nsmh.css","previous":3186,"size":5157,"diff":1971},{"filename":"index.html","previous":454,"size":456,"diff":2}]},{"timestamp":1653894868796,"files":[{"filename":"bundle.*****.js","previous":18220,"size":18732,"diff":512},{"filename":"polyfills.*****.js","previous":2136,"size":2136,"diff":0},{"filename":"assets/css/nsmh.css","previous":3186,"size":3186,"diff":0},{"filename":"index.html","previous":455,"size":454,"diff":-1}]},{"timestamp":1653849008007,"files":[{"filename":"sw.js","previous":6668,"size":0,"diff":-6668},{"filename":"bundle.*****.js","previous":18278,"size":18220,"diff":-58},{"filename":"polyfills.*****.js","previous":2136,"size":2136,"diff":0},{"filename":"assets/css/nsmh.css","previous":3186,"size":3186,"diff":0},{"filename":"index.html","previous":455,"size":455,"diff":0},{"filename":"200.html","previous":441,"size":0,"diff":-441}]},{"timestamp":1653848944794,"files":[{"filename":"sw.js","previous":6667,"size":6668,"diff":1},{"filename":"bundle.*****.js","previous":15289,"size":18278,"diff":2989},{"filename":"polyfills.*****.js","previous":2136,"size":2136,"diff":0},{"filename":"assets/css/nsmh.css","previous":2408,"size":3186,"diff":778},{"filename":"index.html","previous":457,"size":455,"diff":-2},{"filename":"200.html","previous":443,"size":441,"diff":-2}]},{"timestamp":1653757234679,"files":[{"filename":"sw.js","previous":0,"size":6667,"diff":6667},{"filename":"bundle.*****.js","previous":0,"size":15289,"diff":15289},{"filename":"polyfills.*****.js","previous":0,"size":2136,"diff":2136},{"filename":"assets/css/nsmh.css","previous":0,"size":2408,"diff":2408},{"filename":"index.html","previous":0,"size":457,"diff":457},{"filename":"200.html","previous":0,"size":443,"diff":443}]}]
